autoapi/__init__.py
autoapi/app.py
autoapi/dependencies.py
autoapi/settings.py
autoapi/api/__init__.py
autoapi/api/encoders.py
autoapi/api/response.py
autoapi/api/http_explorer/__init__.py
autoapi/api/http_explorer/interface.py
autoapi/api/http_explorer/openapi_views.py
autoapi/api/http_explorer/swagger.py
autoapi/api/routes/__init__.py
autoapi/api/routes/interface.py
autoapi/api/routes/urls.py
autoapi/api/routes/django/__init__.py
autoapi/api/routes/django/base.py
autoapi/api/routes/django/http.py
autoapi/api/schema_presenter/__init__.py
autoapi/api/schema_presenter/interface.py
autoapi/api/schema_presenter/openapi/__init__.py
autoapi/api/schema_presenter/openapi/presenter.py
autoapi/api/schema_presenter/openapi/property_presenter.py
autoapi/api/schema_presenter/openapi/properties/__init__.py
autoapi/api/schema_presenter/openapi/properties/any.py
autoapi/api/schema_presenter/openapi/properties/boolean.py
autoapi/api/schema_presenter/openapi/properties/date.py
autoapi/api/schema_presenter/openapi/properties/datetime.py
autoapi/api/schema_presenter/openapi/properties/empty.py
autoapi/api/schema_presenter/openapi/properties/file_.py
autoapi/api/schema_presenter/openapi/properties/float.py
autoapi/api/schema_presenter/openapi/properties/integer.py
autoapi/api/schema_presenter/openapi/properties/interface.py
autoapi/api/schema_presenter/openapi/properties/model.py
autoapi/api/schema_presenter/openapi/properties/string.py
autoapi/api/schema_presenter/openapi/properties/time.py
autoapi/auth/__init__.py
autoapi/auth/interface.py
autoapi/auth/provider.py
autoapi/auth/vars.py
autoapi/schema/__init__.py
autoapi/schema/annotation.py
autoapi/schema/data.py
autoapi/schema/empty.py
autoapi/schema/enums.py
autoapi/schema/interfaces.py
autoapi/schema/method.py
autoapi/schema/service.py
autoapi/schema/types.py
autoapi/schema/utils.py
autoapi/schema/parsers/__init__.py
autoapi/schema/parsers/dataclass.py
autoapi/schema/parsers/date.py
autoapi/schema/parsers/datetime.py
autoapi_django-0.11.4.dist-info/LICENSE.txt
autoapi_django-0.11.4.dist-info/METADATA
autoapi_django-0.11.4.dist-info/WHEEL
autoapi_django-0.11.4.dist-info/top_level.txt
autoapi_django-0.11.4.dist-info/RECORD
