Metadata-Version: 2.1
Name: autoapi-django
Version: 0.11.4
Summary: Library for generating transport logic for web application
Author-email: Artem Romanukov <vens148@gmail.com>
License: The MIT License (MIT)
Project-URL: homepage, https://github.com/romanukov/autoapi/
Project-URL: documentation, https://github.com/romanukov/autoapi/
Project-URL: repository, https://github.com/romanukov/autoapi/
Keywords: api,django,swagger,openapi
Classifier: Topic :: Software Development
Requires-Python: >=3.9
License-File: LICENSE.txt
Requires-Dist: Django <5,>=4.1
Requires-Dist: django-cors-headers <3.15,>=3.14
Requires-Dist: requests <2.29,>=2.28
Requires-Dist: Pillow <9.6,>=9.5.0
Requires-Dist: python-magic ==0.4.27
Requires-Dist: python-dateutil ==2.8.2
